seal/__init__.py
seal/ast.py
seal/cli.py
seal/config.py
seal/langspec.json
seal/langspec.py
seal/scanner.py
seal_lang-0.0.1.dist-info/METADATA
seal_lang-0.0.1.dist-info/WHEEL
seal_lang-0.0.1.dist-info/entry_points.txt
seal_lang-0.0.1.dist-info/top_level.txt
seal_lang-0.0.1.dist-info/RECORD
