Metadata-Version: 2.1
Name: seal-lang
Version: 0.0.1
Summary: Write meaningful teal in s-expressions!
Home-page: https://github.com/kadirpekel/seal
Author: Kadir Pekel
Author-email: kadirpekel@gmail.com
Requires-Python: >=3.7
Requires-Dist: komandr (>=2.0.1)
Provides-Extra: dev
Requires-Dist: pytest ; extra == 'dev'
Requires-Dist: flake8 ; extra == 'dev'
